blocksnet/__init__.py
blocksnet/method/__init__.py
blocksnet/method/accessibility.py
blocksnet/method/annealing_optimizer.py
blocksnet/method/base_method.py
blocksnet/method/centrality.py
blocksnet/method/connectivity.py
blocksnet/method/diversity.py
blocksnet/method/integration.py
blocksnet/method/land_use_prediction.py
blocksnet/method/population_centrality.py
blocksnet/method/provision.py
blocksnet/method/spacematrix.py
blocksnet/method/vacant_area.py
blocksnet/method/weighted_connectivity.py
blocksnet/models/__init__.py
blocksnet/models/city.py
blocksnet/models/land_use.py
blocksnet/models/schema.py
blocksnet/models/service_type.py
blocksnet/preprocessing/__init__.py
blocksnet/preprocessing/accessibility_processor.py
blocksnet/preprocessing/blocks_generator.py
blocksnet/preprocessing/blocks_splitter.py
blocksnet/preprocessing/land_use_optimizer.py
blocksnet/preprocessing/land_use_processor.py
blocksnet/utils/__init__.py
blocksnet/utils/helpers.py
blocksnet/utils/service_types.py
blocksnet-0.1.0.dist-info/LICENSE
blocksnet-0.1.0.dist-info/METADATA
blocksnet-0.1.0.dist-info/WHEEL
blocksnet-0.1.0.dist-info/top_level.txt
blocksnet-0.1.0.dist-info/RECORD
