Metadata-Version: 2.2
Name: blocksnet
Version: 0.1.0
Summary: Package provides methods of master plan requirements automated generation for urban areas
Project-URL: Repository, https://github.com/aimclub/blocksnet
Project-URL: Bug Tracker, https://github.com/aimclub/blocksnet/issues
Classifier: Programming Language :: Python :: 3
Classifier: License :: OSI Approved :: BSD License
Classifier: Operating System :: OS Independent
Classifier: Intended Audience :: Science/Research
Requires-Python: >=3.10
License-File: LICENSE
Requires-Dist: geopandas<1.0.0,>=0.13.0
Requires-Dist: loguru<1.0.0,>=0.7.0
Requires-Dist: matplotlib==3.7.1
Requires-Dist: networkit<12.0,>=11.0
Requires-Dist: networkx<4.0,>=3.1
Requires-Dist: numpy==1.23.5
Requires-Dist: osmnx<2.0.0,>=1.6.0
Requires-Dist: pandas<3.0.0,>=2.0.0
Requires-Dist: pandera==0.20.2
Requires-Dist: PuLP==2.7.0
Requires-Dist: pyarrow==12.0.0
Requires-Dist: pydantic<3.0.0,>=2.0.0
Requires-Dist: scikit-learn==1.2.2
Requires-Dist: scipy<2.0.0,>=1.10.1
Requires-Dist: shapely==2.0.1
Requires-Dist: tqdm<5.0.0,>=4.65.0
Requires-Dist: voronoi-diagram-for-polygons==0.1.6
Requires-Dist: momepy==0.7.0
Requires-Dist: iduedu==0.1.2
Provides-Extra: dev
Requires-Dist: black[jupyter]>=22; extra == "dev"
Requires-Dist: mapclassify==2.6.1; extra == "dev"
Requires-Dist: folium==0.14.0; extra == "dev"
Requires-Dist: matplotlib-inline==0.1.6; extra == "dev"
Requires-Dist: ipykernel; extra == "dev"
Requires-Dist: jupyter; extra == "dev"
Requires-Dist: ipywidgets; extra == "dev"
Requires-Dist: isort>=5.6; extra == "dev"
Requires-Dist: pylint>=2.17; extra == "dev"
Requires-Dist: pre-commit>=3.1; extra == "dev"
Requires-Dist: pytest==7.4.3; extra == "dev"
Requires-Dist: pytest-cov==4.1.0; extra == "dev"
Requires-Dist: build; extra == "dev"
Requires-Dist: twine; extra == "dev"
Provides-Extra: docs
Requires-Dist: docutils<0.19,>=0.18.1; extra == "docs"
Requires-Dist: sphinx==6.2.1; extra == "docs"
Requires-Dist: sphinx-book-theme==1.0.1; extra == "docs"
Requires-Dist: nbsphinx==0.9.3; extra == "docs"
Requires-Dist: nbsphinx-link==1.3.0; extra == "docs"
Requires-Dist: numpydoc==1.5.0; extra == "docs"
Requires-Dist: autodocsumm==0.2.12; extra == "docs"
Requires-Dist: myst_parser<4.0.0,>=3.0.0; extra == "docs"
Requires-Dist: sphinx_rtd_theme<2.0.0,>=1.2.0; extra == "docs"
Requires-Dist: pandoc<3.0.0,>=2.0.0; extra == "docs"
